README
setup.py
stm/__init__.py
stm/datatypes.py
stm/eventloop.py
stm/timeout.py
stm/utils.py
stm.egg-info/PKG-INFO
stm.egg-info/SOURCES.txt
stm.egg-info/dependency_links.txt
stm.egg-info/requires.txt
stm.egg-info/top_level.txt