Metadata-Version: 1.0
Name: stm
Version: 0.2.7
Summary: A software transactional memory library
Home-page: UNKNOWN
Author: Alexander Boyd
Author-email: alex@opengroove.org
License: UNKNOWN
Platform: UNKNOWN
